dopple_ai_client/__init__.py
dopple_ai_client/api_urls.py
dopple_ai_client/bot.py
dopple_ai_client/chat.py
dopple_ai_client/dopple_client.py
dopple_ai_client/dopple_request.py
dopple_ai_client/dopple_request_error.py
dopple_ai_client/message.py
dopple_ai_client/response.py
dopple_ai_client/user_data.py
dopple_ai_client-1.3.0.1.dist-info/LICENSE
dopple_ai_client-1.3.0.1.dist-info/METADATA
dopple_ai_client-1.3.0.1.dist-info/WHEEL
dopple_ai_client-1.3.0.1.dist-info/top_level.txt
dopple_ai_client-1.3.0.1.dist-info/RECORD
