Metadata-Version: 2.1
Name: dopple_ai_client
Version: 1.3.0.1
Summary: Python API wrapper for Dopple.AI
Home-page: https://github.com/Crimeraaa-S1GMA/DoppleAIClient
Author: crimeraaa
Author-email: majkelipytania@gmail.com
License: MIT
Requires-Python: >=3.8
License-File: LICENSE
